Semestrul 4/Calculatoare-numerice/Laborator/Proiecte_Lab/ALU-main/src/dff.v
module dff #(parameter WIDTH = 1)(
  input              clk,
  input              reset_n,
  input  [WIDTH-1:0] d,
  output [WIDTH-1:0] q
);
  reg [WIDTH-1:0] q_reg;
  assign q = q_reg;
  always @(posedge clk or negedge reset_n) begin
    if (!reset_n)
      q_reg <= {WIDTH{1'b0}};
    else
      q_reg <= d;
  end
endmodule

Semestrul 4/Calculatoare-numerice/Laborator/Proiecte_Lab/ALU-main/src/fac.v
module fac(
    input x, y, ci,
    output z, co
);
    assign z = x ^ y ^ ci;
    assign co = (x & y) | (x & ci) | (y & ci);
endmodule

Semestrul 4/Calculatoare-numerice/Laborator/Proiecte_Lab/ALU-main/src/adder.v


module adder #(
    parameter WIDTH = 8
)(
    input [WIDTH-1:0] a,
    input [WIDTH-1:0] b,
    input cin,
    input en,
    output [WIDTH:0] sum
);
    wire [WIDTH-1:0] c;
    wire [WIDTH-1:0] s;

    fac f0(a[0], b[0], cin, s[0], c[0]);

    generate
        genvar i;
        for (i = 1; i < WIDTH; i = i + 1) begin : rca
            fac f(a[i], b[i], c[i-1], s[i], c[i]);
        end
    endgenerate
    
    assign sum = en ? {c[WIDTH-1], s} : 20;
endmodule

// module adder_tb;
//     reg [7:0] a;
//     reg [7:0] b;
//     reg cin;
//     reg en = 1'b1;
//     wire [8:0] sum;

//     adder #(.WIDTH(8)) uut (
//         .a(a),
//         .b(b),
//         .cin(cin),
//         .en(en),
//         .sum(sum)
//     );

//     integer k;

//     initial begin
//         for(k = 0; k < 10000; k = k + 1) begin
//             {a, b, cin} = k;
//             #10;
//             $display("a=%d b=%d cin=%d sum=%d sum8=%d", a, b, cin, sum[7:0], sum[8]);
//         end
//     end

// endmodule

Semestrul 4/Calculatoare-numerice/Laborator/Proiecte_Lab/ALU-main/src/leftshifter.v
module leftshifter #(
    parameter WIDTH = 8       
)(
    input  [WIDTH-1:0] in,
    input serial_in,
    output [WIDTH-1:0] out
);
    // LSB is zero after shift
    assign out[0] = serial_in;

    // For bit i>0, out[i] gets in[i-1]
    genvar i;
    generate
      for (i = 1; i < WIDTH; i = i + 1) begin : bit_shift
        assign out[i] = in[i-1];
      end
    endgenerate
endmodule

Semestrul 4/Calculatoare-numerice/Laborator/Proiecte_Lab/ALU-main/src/divider.v
`timescale 1ns/1ps
`include "adder.v"
`include "dff.v"
`include "fac.v"
`include "leftshifter.v"
// -------------------------
// Divider Module
// -------------------------
module divider (
    input  wire        clk,
    input  wire        reset_n,
    input  wire        start,
    input  wire [7:0]  a,      // dividend
    input  wire [7:0]  b,      // divisor
    output wire [15:0] o,      // { quotient, remainder }
    output wire        done
);

  // Combined register: {R, Q} initialization:
  wire [15:0] reg_data, reg_data_next;
  wire [15:0] init_val;
  assign init_val = {8'd0, a};

  // 4-bit counter for 8 iterations:
  wire [3:0] count, count_next;
  assign count_next = start ? 4'd8 : (count - 4'd1);

  // One iteration: shift combined register left by one.
  wire [15:0] shifted;
  leftshifter #(.WIDTH(16)) shifter (
      .in(reg_data),
      .serial_in(1'b0),
      .out(shifted)
  );
  
  // Extract remainder and quotient parts.
  wire [7:0] R_sh, Q_sh;
  assign R_sh = shifted[15:8];
  assign Q_sh = shifted[7:0];

  // Compute R_sh - b and R_sh + b.
  wire [8:0] sub_out, add_out;
  adder #(.WIDTH(8)) sub_adder (
      .a(R_sh),
      .b(~b),
      .cin(1'b1),
      .en(1'b1),
      .sum(sub_out)
  );
  adder #(.WIDTH(8)) add_adder (
      .a(R_sh),
      .b(b),
      .cin(1'b0),
      .en(1'b1),
      .sum(add_out)
  );

  // Choose the proper result.
  wire [7:0] R_temp;
  assign R_temp = (R_sh[7] == 1'b0) ? sub_out[7:0] : add_out[7:0];

  // Determine quotient bit.
  wire qbit;
  assign qbit = (R_temp[7] == 1'b0) ? 1'b1 : 1'b0;

  // Form new quotient and remainder.
  wire [7:0] Q_new;
  assign Q_new = { Q_sh[7:1], qbit };
  assign reg_data_next = { R_temp, Q_new };
  
  // Final Correction
  wire [7:0] final_R, final_Q;
  wire [8:0] final_corr;
  assign final_R = reg_data[15:8];
  assign final_Q = reg_data[7:0];
  
  adder #(.WIDTH(8)) final_correction (
      .a(final_R),
      .b(b),
      .cin(1'b0),
      .en(1'b1),
      .sum(final_corr)
  );
  wire [7:0] corrected_R;
  assign corrected_R = (final_R[7] == 1'b1) ? final_corr[7:0] : final_R;

  assign o = { final_Q, corrected_R };
  assign done = (count == 4'd0);

  // Registers for combined data and counter.
  dff #(.WIDTH(16)) reg_data_dff (
      .clk(clk),
      .reset_n(reset_n),
      .d(start ? init_val : reg_data_next),
      .q(reg_data)
  );
  dff #(.WIDTH(4)) count_dff (
      .clk(clk),
      .reset_n(reset_n),
      .d(count_next),
      .q(count)
  );  

endmodule

// -------------------------
// Testbench Module for Divider
// -------------------------
module divider_tb;
  reg         clk;
  reg         reset_n;
  reg         start;
  reg  [7:0]  a, b;
  wire [15:0] o;
  wire        done;
  
  divider uut (
      .clk(clk),
      .reset_n(reset_n),
      .start(start),
      .a(a),
      .b(b),
      .o(o),
      .done(done)
  );
  
  // Clock generation
  initial begin
    clk = 0;
    forever #5 clk = ~clk;
  end

  // Helper task for testing division
  task test_div(input [7:0] dividend, input [7:0] divisor);
    begin
      reset_n = 0; start = 0;
      #10; reset_n = 1; #5;
      a = dividend; b = divisor;
      start = 1; #10; start = 0;
      wait(done); #5;
      $display("%d ÷ %d: quotient = %d, remainder = %d", dividend, divisor, o[15:8], o[7:0]);
    end
  endtask
  
  // Testbench stimuli with additional tests
  initial begin
    $dumpfile("divider_tb.vcd");
    $dumpvars(0, divider_tb);
    
    // Test Cases
    test_div(8'd15, 8'd3);     // Expected: 5, remainder 0.
    test_div(8'd100, 8'd9);    // Expected: approx. 11, remainder ~1.
    test_div(8'd0, 8'd1);      // Expected: 0, remainder 0.
    test_div(8'd255, 8'd1);    // Expected: 255, remainder 0.
    test_div(8'd1, 8'd255);    // Expected: 0, remainder 1.
    test_div(8'd128, 8'd2);    // Expected: 64, remainder 0.
    test_div(8'd255, 8'd255);  // Expected: 1, remainder 0.
    test_div(8'd5, 8'd2);      // Expected: 2, remainder 1.
    
    // Additional edge cases...
    test_div(8'd250, 8'd5);    // 250 ÷ 5: Expected: 50, remainder 0.
    test_div(8'd37, 8'd7);     // 37 ÷ 7.
    
    $finish;
  end
endmodule

Semestrul 4/Calculatoare-numerice/Laborator/Proiecte_Lab/ALU-main/src/divider_tb.vcd
$date
	Sat Apr 26 16:18:27 2025
$end
$version
	Icarus Verilog
$end
$timescale
	1ps
$end
$scope module divider_tb $end
$var wire 16 ! o [15:0] $end
$var wire 1 " done $end
$var reg 8 # a [7:0] $end
$var reg 8 $ b [7:0] $end
$var reg 1 % clk $end
$var reg 1 & reset_n $end
$var reg 1 ' start $end
$scope module uut $end
$var wire 8 ( a [7:0] $end
$var wire 8 ) b [7:0] $end
$var wire 1 % clk $end
$var wire 1 & reset_n $end
$var wire 1 ' start $end
$var wire 9 * sub_out [8:0] $end
$var wire 16 + shifted [15:0] $end
$var wire 16 , reg_data_next [15:0] $end
$var wire 16 - reg_data [15:0] $end
$var wire 1 . qbit $end
$var wire 16 / o [15:0] $end
$var wire 16 0 init_val [15:0] $end
$var wire 9 1 final_corr [8:0] $end
$var wire 8 2 final_R [7:0] $end
$var wire 8 3 final_Q [7:0] $end
$var wire 1 " done $end
$var wire 4 4 count_next [3:0] $end
$var wire 4 5 count [3:0] $end
$var wire 8 6 corrected_R [7:0] $end
$var wire 9 7 add_out [8:0] $end
$var wire 8 8 R_temp [7:0] $end
$var wire 8 9 R_sh [7:0] $end
$var wire 8 : Q_sh [7:0] $end
$var wire 8 ; Q_new [7:0] $end
$scope module add_adder $end
$var wire 8 < a [7:0] $end
$var wire 8 = b [7:0] $end
$var wire 1 > cin $end
$var wire 1 ? en $end
$var wire 9 @ sum [8:0] $end
$var wire 8 A s [7:0] $end
$var wire 8 B c [7:0] $end
$var parameter 32 C WIDTH $end
$scope begin rca[1] $end
$var parameter 2 D i $end
$scope module f $end
$var wire 1 E ci $end
$var wire 1 F co $end
$var wire 1 G x $end
$var wire 1 H y $end
$var wire 1 I z $end
$upscope $end
$upscope $end
$scope begin rca[2] $end
$var parameter 3 J i $end
$scope module f $end
$var wire 1 K ci $end
$var wire 1 L co $end
$var wire 1 M x $end
$var wire 1 N y $end
$var wire 1 O z $end
$upscope $end
$upscope $end
$scope begin rca[3] $end
$var parameter 3 P i $end
$scope module f $end
$var wire 1 Q ci $end
$var wire 1 R co $end
$var wire 1 S x $end
$var wire 1 T y $end
$var wire 1 U z $end
$upscope $end
$upscope $end
$scope begin rca[4] $end
$var parameter 4 V i $end
$scope module f $end
$var wire 1 W ci $end
$var wire 1 X co $end
$var wire 1 Y x $end
$var wire 1 Z y $end
$var wire 1 [ z $end
$upscope $end
$upscope $end
$scope begin rca[5] $end
$var parameter 4 \ i $end
$scope module f $end
$var wire 1 ] ci $end
$var wire 1 ^ co $end
$var wire 1 _ x $end
$var wire 1 ` y $end
$var wire 1 a z $end
$upscope $end
$upscope $end
$scope begin rca[6] $end
$var parameter 4 b i $end
$scope module f $end
$var wire 1 c ci $end
$var wire 1 d co $end
$var wire 1 e x $end
$var wire 1 f y $end
$var wire 1 g z $end
$upscope $end
$upscope $end
$scope begin rca[7] $end
$var parameter 4 h i $end
$scope module f $end
$var wire 1 i ci $end
$var wire 1 j co $end
$var wire 1 k x $end
$var wire 1 l y $end
$var wire 1 m z $end
$upscope $end
$upscope $end
$scope module f0 $end
$var wire 1 > ci $end
$var wire 1 n co $end
$var wire 1 o x $end
$var wire 1 p y $end
$var wire 1 q z $end
$upscope $end
$upscope $end
$scope module count_dff $end
$var wire 1 % clk $end
$var wire 4 r d [3:0] $end
$var wire 1 & reset_n $end
$var wire 4 s q [3:0] $end
$var parameter 32 t WIDTH $end
$var reg 4 u q_reg [3:0] $end
$upscope $end
$scope module final_correction $end
$var wire 8 v a [7:0] $end
$var wire 8 w b [7:0] $end
$var wire 1 x cin $end
$var wire 1 y en $end
$var wire 9 z sum [8:0] $end
$var wire 8 { s [7:0] $end
$var wire 8 | c [7:0] $end
$var parameter 32 } WIDTH $end
$scope begin rca[1] $end
$var parameter 2 ~ i $end
$scope module f $end
$var wire 1 !" ci $end
$var wire 1 "" co $end
$var wire 1 #" x $end
$var wire 1 $" y $end
$var wire 1 %" z $end
$upscope $end
$upscope $end
$scope begin rca[2] $end
$var parameter 3 &" i $end
$scope module f $end
$var wire 1 '" ci $end
$var wire 1 (" co $end
$var wire 1 )" x $end
$var wire 1 *" y $end
$var wire 1 +" z $end
$upscope $end
$upscope $end
$scope begin rca[3] $end
$var parameter 3 ," i $end
$scope module f $end
$var wire 1 -" ci $end
$var wire 1 ." co $end
$var wire 1 /" x $end
$var wire 1 0" y $end
$var wire 1 1" z $end
$upscope $end
$upscope $end
$scope begin rca[4] $end
$var parameter 4 2" i $end
$scope module f $end
$var wire 1 3" ci $end
$var wire 1 4" co $end
$var wire 1 5" x $end
$var wire 1 6" y $end
$var wire 1 7" z $end
$upscope $end
$upscope $end
$scope begin rca[5] $end
$var parameter 4 8" i $end
$scope module f $end
$var wire 1 9" ci $end
$var wire 1 :" co $end
$var wire 1 ;" x $end
$var wire 1 <" y $end
$var wire 1 =" z $end
$upscope $end
$upscope $end
$scope begin rca[6] $end
$var parameter 4 >" i $end
$scope module f $end
$var wire 1 ?" ci $end
$var wire 1 @" co $end
$var wire 1 A" x $end
$var wire 1 B" y $end
$var wire 1 C" z $end
$upscope $end
$upscope $end
$scope begin rca[7] $end
$var parameter 4 D" i $end
$scope module f $end
$var wire 1 E" ci $end
$var wire 1 F" co $end
$var wire 1 G" x $end
$var wire 1 H" y $end
$var wire 1 I" z $end
$upscope $end
$upscope $end
$scope module f0 $end
$var wire 1 x ci $end
$var wire 1 J" co $end
$var wire 1 K" x $end
$var wire 1 L" y $end
$var wire 1 M" z $end
$upscope $end
$upscope $end
$scope module reg_data_dff $end
$var wire 1 % clk $end
$var wire 16 N" d [15:0] $end
$var wire 1 & reset_n $end
$var wire 16 O" q [15:0] $end
$var parameter 32 P" WIDTH $end
$var reg 16 Q" q_reg [15:0] $end
$upscope $end
$scope module shifter $end
$var wire 16 R" in [15:0] $end
$var wire 1 S" serial_in $end
$var wire 16 T" out [15:0] $end
$var parameter 32 U" WIDTH $end
$scope begin bit_shift[1] $end
$var parameter 2 V" i $end
$upscope $end
$scope begin bit_shift[2] $end
$var parameter 3 W" i $end
$upscope $end
$scope begin bit_shift[3] $end
$var parameter 3 X" i $end
$upscope $end
$scope begin bit_shift[4] $end
$var parameter 4 Y" i $end
$upscope $end
$scope begin bit_shift[5] $end
$var parameter 4 Z" i $end
$upscope $end
$scope begin bit_shift[6] $end
$var parameter 4 [" i $end
$upscope $end
$scope begin bit_shift[7] $end
$var parameter 4 \" i $end
$upscope $end
$scope begin bit_shift[8] $end
$var parameter 5 ]" i $end
$upscope $end
$scope begin bit_shift[9] $end
$var parameter 5 ^" i $end
$upscope $end
$scope begin bit_shift[10] $end
$var parameter 5 _" i $end
$upscope $end
$scope begin bit_shift[11] $end
$var parameter 5 `" i $end
$upscope $end
$scope begin bit_shift[12] $end
$var parameter 5 a" i $end
$upscope $end
$scope begin bit_shift[13] $end
$var parameter 5 b" i $end
$upscope $end
$scope begin bit_shift[14] $end
$var parameter 5 c" i $end
$upscope $end
$scope begin bit_shift[15] $end
$var parameter 5 d" i $end
$upscope $end
$upscope $end
$scope module sub_adder $end
$var wire 8 e" a [7:0] $end
$var wire 8 f" b [7:0] $end
$var wire 1 g" cin $end
$var wire 1 h" en $end
$var wire 9 i" sum [8:0] $end
$var wire 8 j" s [7:0] $end
$var wire 8 k" c [7:0] $end
$var parameter 32 l" WIDTH $end
$scope begin rca[1] $end
$var parameter 2 m" i $end
$scope module f $end
$var wire 1 n" ci $end
$var wire 1 o" co $end
$var wire 1 p" x $end
$var wire 1 q" y $end
$var wire 1 r" z $end
$upscope $end
$upscope $end
$scope begin rca[2] $end
$var parameter 3 s" i $end
$scope module f $end
$var wire 1 t" ci $end
$var wire 1 u" co $end
$var wire 1 v" x $end
$var wire 1 w" y $end
$var wire 1 x" z $end
$upscope $end
$upscope $end
$scope begin rca[3] $end
$var parameter 3 y" i $end
$scope module f $end
$var wire 1 z" ci $end
$var wire 1 {" co $end
$var wire 1 |" x $end
$var wire 1 }" y $end
$var wire 1 ~" z $end
$upscope $end
$upscope $end
$scope begin rca[4] $end
$var parameter 4 !# i $end
$scope module f $end
$var wire 1 "# ci $end
$var wire 1 ## co $end
$var wire 1 $# x $end
$var wire 1 %# y $end
$var wire 1 &# z $end
$upscope $end
$upscope $end
$scope begin rca[5] $end
$var parameter 4 '# i $end
$scope module f $end
$var wire 1 (# ci $end
$var wire 1 )# co $end
$var wire 1 *# x $end
$var wire 1 +# y $end
$var wire 1 ,# z $end
$upscope $end
$upscope $end
$scope begin rca[6] $end
$var parameter 4 -# i $end
$scope module f $end
$var wire 1 .# ci $end
$var wire 1 /# co $end
$var wire 1 0# x $end
$var wire 1 1# y $end
$var wire 1 2# z $end
$upscope $end
$upscope $end
$scope begin rca[7] $end
$var parameter 4 3# i $end
$scope module f $end
$var wire 1 4# ci $end
$var wire 1 5# co $end
$var wire 1 6# x $end
$var wire 1 7# y $end
$var wire 1 8# z $end
$upscope $end
$upscope $end
$scope module f0 $end
$var wire 1 g" ci $end
$var wire 1 9# co $end
$var wire 1 :# x $end
$var wire 1 ;# y $end
$var wire 1 <# z $end
$upscope $end
$upscope $end
$upscope $end
$scope task test_div $end
$var reg 8 =# dividend [7:0] $end
$var reg 8 ># divisor [7:0] $end
$upscope $end
$upscope $end
$enddefinitions $end
$comment Show the parameter values. $end
$dumpall
b111 3#
b110 -#
b101 '#
b100 !#
b11 y"
b10 s"
b1 m"
b1000 l"
b1111 d"
b1110 c"
b1101 b"
b1100 a"
b1011 `"
b1010 _"
b1001 ^"
b1000 ]"
b111 \"
b110 ["
b101 Z"
b100 Y"
b11 X"
b10 W"
b1 V"
b10000 U"
b10000 P"
b111 D"
b110 >"
b101 8"
b100 2"
b11 ,"
b10 &"
b1 ~
b1000 }
b100 t
b111 h
b110 b
b101 \
b100 V
b11 P
b10 J
b1 D
b1000 C
$end
#0
$dumpvars
b11 >#
b1111 =#
x<#
x;#
0:#
x9#
x8#
x7#
06#
x5#
x4#
x2#
x1#
00#
x/#
x.#
x,#
x+#
0*#
x)#
x(#
x&#
x%#
0$#
x##
x"#
x~"
x}"
0|"
x{"
xz"
xx"
xw"
0v"
xu"
xt"
xr"
xq"
0p"
xo"
xn"
bx k"
bx j"
bx i"
1h"
1g"
bx f"
b0 e"
b0 T"
0S"
b0 R"
b0 Q"
b0 O"
bx0000000x N"
xM"
xL"
0K"
0J"
xI"
xH"
0G"
0F"
0E"
xC"
xB"
0A"
0@"
0?"
x="
x<"
0;"
0:"
09"
x7"
x6"
05"
04"
03"
x1"
x0"
0/"
0."
0-"
x+"
x*"
0)"
0("
0'"
x%"
x$"
0#"
0""
0!"
b0 |
bx {
b0xxxxxxxx z
1y
0x
bx w
b0 v
b0 u
b0 s
b1111 r
xq
xp
0o
0n
xm
xl
0k
0j
0i
xg
xf
0e
0d
0c
xa
x`
0_
0^
0]
x[
xZ
0Y
0X
0W
xU
xT
0S
0R
0Q
xO
xN
0M
0L
0K
xI
xH
0G
0F
0E
b0 B
bx A
b0xxxxxxxx @
1?
0>
bx =
b0 <
b0x ;
b0 :
b0 9
bx 8
b0xxxxxxxx 7
b0 6
b0 5
b1111 4
b0 3
b0 2
b0xxxxxxxx 1
b0xxxxxxxx 0
b0 /
x.
b0 -
bx0000000x ,
b0 +
bx *
bx )
bx (
0'
0&
0%
bx $
bx #
1"
b0 !
$end
#5000
1%
#10000
0%
1&
#15000
b11110 :
b11110 +
b11110 T"
b111100000000 !
b111100000000 /
b1111 3
b1111 -
b1111 O"
b1111 Q"
b1111 R"
0"
b1000 5
b1000 s
b1000 u
b11110 ;
0.
05#
18#
04#
0/#
12#
0.#
0)#
1,#
0(#
0##
1&#
0"#
0{"
1~"
0z"
0u"
1x"
b1111110100011110 ,
b11111101 8
0r"
0t"
0n"
0o"
b11111101 *
b11111101 i"
b11111101 j"
1<#
b0 k"
09#
1I
0O
0U
0[
0a
0g
0m
b11 7
b11 @
b11 A
1q
1%"
0+"
01"
07"
0="
0C"
0I"
b11 1
b11 z
b11 {
1M"
0q"
1w"
1}"
1%#
1+#
11#
17#
0;#
b1000 4
b1000 r
b1111 N"
b11111100 f"
1H
0N
0T
0Z
0`
0f
0l
1p
1$"
0*"
00"
06"
0<"
0B"
0H"
1L"
1%
1'
b11 $
b11 )
b11 =
b11 w
b1111 0
b1111 #
b1111 (
#20000
0%
#25000
1F"
1E"
1@"
1?"
1:"
19"
14"
13"
1."
1-"
1("
1'"
0.
1O
1""
1K
1"#
1(#
1.#
14#
0%"
b10 B
1F
1{"
1##
1)#
1/#
b11111000 k"
15#
1!"
b11111101 8
0I
1U
1[
1a
1g
b11111101 7
b11111101 @
b11111101 A
1m
1r"
0~"
1&#
1,#
12#
b111110111 *
b111110111 i"
b11110111 j"
18#
b11111111 |
1J"
0+"
01"
07"
0="
0C"
0I"
b100000000 1
b100000000 z
b0 {
0M"
b1111110100111100 ,
b111100 ;
1G
1S
1Y
1_
1e
1k
1p"
1|"
1$#
1*#
10#
16#
b111100 :
b11111010 9
b11111010 <
b11111010 e"
b0 6
1)"
1/"
15"
1;"
1A"
1G"
1K"
b1111101000111100 +
b1111101000111100 T"
b1111000000000 !
b1111000000000 /
b11110 3
b11111101 2
b11111101 v
b111 5
b111 s
b111 u
b1111110100011110 -
b1111110100011110 O"
b1111110100011110 Q"
b1111110100011110 R"
b110 4
b110 r
b1111110100111100 N"
1%
0'
#30000
0%
#35000
b1111110101111000 N"
b1111110101111000 ,
b1111000 ;
b1111000 :
b1111101001111000 +
b1111101001111000 T"
b11110000000000 !
b11110000000000 /
b111100 3
b101 4
b101 r
b1111110100111100 -
b1111110100111100 O"
b1111110100111100 Q"
b1111110100111100 R"
b110 5
b110 s
b110 u
1%
#40000
0%
#45000
b1111110111110000 N"
b1111110111110000 ,
b11110000 ;
b11110000 :
b100 4
b100 r
b1111101011110000 +
b1111101011110000 T"
b111100000000000 !
b111100000000000 /
b1111000 3
b101 5
b101 s
b101 u
b1111110101111000 -
b1111110101111000 O"
b1111110101111000 Q"
b1111110101111000 R"
1%
#50000
0%
#55000
1~"
1z"
1u"
0x"
1t"
1o"
1I
0r"
b11111110 8
1E
1n"
b11 B
1n
b11111111 k"
19#
b11111110 7
b11111110 @
b11111110 A
0q
b111111000 *
b111111000 i"
b11111000 j"
0<#
b1111111011100000 N"
b1111111011100000 ,
b11100000 ;
1o
1:#
b11100000 :
b11111011 9
b11111011 <
b11111011 e"
b1111101111100000 +
b1111101111100000 T"
b1111000000000000 !
b1111000000000000 /
b11110000 3
b11 4
b11 r
b1111110111110000 -
b1111110111110000 O"
b1111110111110000 Q"
b1111110111110000 R"
b100 5
b100 s
b100 u
1%
#60000
0%
#65000
1.
1j
0m
1i
1d
0g
1c
1^
0a
1]
1X
0[
1W
1R
0U
b0 8
1Q
0t"
b11111111 B
1L
b11111101 k"
0o"
b1 6
0!"
0I
b100000000 7
b100000000 @
b0 A
0O
1r"
b111111010 *
b111111010 i"
b11111010 j"
0x"
b11111110 |
0J"
b11000001 N"
0%"
b100000001 1
b100000001 z
b1 {
1M"
b11000001 ,
b11000001 ;
0G
1M
0p"
1v"
b11000000 :
b11111101 9
b11111101 <
b11111101 e"
1#"
0K"
b10 4
b10 r
b1111110111000000 +
b1111110111000000 T"
b1110000000000001 !
b1110000000000001 /
b11100000 3
b11111110 2
b11111110 v
b11 5
b11 s
b11 u
b1111111011100000 -
b1111111011100000 O"
b1111111011100000 Q"
b1111111011100000 R"
1%
#70000
0%
#75000
05#
04#
0/#
0.#
0)#
0(#
0##
0"#
0{"
0.
0Q
0W
0]
0c
0i
0z"
0L
0R
0X
0^
0d
b11 B
0j
b1 k"
0u"
0'"
0-"
03"
09"
0?"
0E"
b11111110 8
1O
0U
0[
0a
0g
b100 7
b100 @
b100 A
0m
1x"
1~"
1&#
1,#
12#
b11111110 *
b11111110 i"
b11111110 j"
18#
0""
0("
0."
04"
0:"
0@"
b0 |
0F"
b1111111010000010 N"
b0 6
1%"
0+"
01"
07"
0="
0C"
b11 1
b11 z
b11 {
0I"
b1111111010000010 ,
b10000010 ;
0M
0S
0Y
0_
0e
0k
0v"
0|"
0$#
0*#
00#
06#
b10000010 :
b1 9
b1 <
b1 e"
0#"
0)"
0/"
05"
0;"
0A"
0G"
b110000010 +
b110000010 T"
b1100000100000000 !
b1100000100000000 /
b11000001 3
b0 2
b0 v
b1 4
b1 r
b11000001 -
b11000001 O"
b11000001 Q"
b11000001 R"
b10 5
b10 s
b10 u
1%
#80000
0%
#85000
1F"
1j
1E"
1@"
1i
1d
1?"
1:"
1c
1^
19"
14"
1]
1X
13"
1."
1W
1R
1-"
1("
1.
1Q
1z"
1"#
1(#
1.#
14#
b11111111 B
1L
1u"
1{"
1##
1)#
1/#
b11111101 k"
15#
1'"
b0 8
0O
0U
0[
0a
0g
b100000000 7
b100000000 @
b0 A
0m
0x"
1~"
1&#
1,#
12#
b111111010 *
b111111010 i"
b11111010 j"
18#
b11111110 |
1""
b101 N"
0%"
0+"
01"
07"
0="
0C"
b100000001 1
b100000001 z
b1 {
0I"
b101 ,
b101 ;
1M
1S
1Y
1_
1e
1k
1v"
1|"
1$#
1*#
10#
16#
b100 :
b11111101 9
b11111101 <
b11111101 e"
b1 6
1#"
1)"
1/"
15"
1;"
1A"
1G"
b0 4
b0 r
b1111110100000100 +
b1111110100000100 T"
b1000001000000001 !
b1000001000000001 /
b10000010 3
b11111110 2
b11111110 v
b1 5
b1 s
b1 u
b1111111010000010 -
b1111111010000010 O"
b1111111010000010 Q"
b1111111010000010 R"
1%
#90000
0%
#95000
05#
04#
0/#
0.#
0)#
0(#
0##
0K
0"#
0F
0{"
0.
1I
0r"
0Q
0W
0]
0c
0i
0E
0z"
0n"
0L
0R
0X
0^
0d
0j
b0 B
0n
0u"
b0 k"
09#
0'"
0-"
03"
09"
0?"
0E"
b11111101 8
0O
0U
0[
0a
0g
0m
b11 7
b11 @
b11 A
1q
1x"
1~"
1&#
1,#
12#
18#
b11111101 *
b11111101 i"
b11111101 j"
1<#
0""
0("
0."
04"
0:"
0@"
b0 |
0F"
b1111110100001010 N"
b0 6
1%"
0+"
01"
07"
0="
0C"
b11 1
b11 z
b11 {
0I"
b1111110100001010 ,
b1010 ;
0M
0S
0Y
0_
0e
0k
0o
0v"
0|"
0$#
0*#
00#
06#
0:#
b1010 :
b0 9
b0 <
b0 e"
0#"
0)"
0/"
05"
0;"
0A"
0G"
b1010 +
b1010 T"
b10100000000 !
b10100000000 /
b101 3
b0 2
b0 v
b1111 4
b1111 r
b101 -
b101 O"
b101 Q"
b101 R"
1"
b0 5
b0 s
b0 u
1%
#100000
b1111110100000000 N"
b1111110100000000 ,
b0 ;
b0 :
b0 +
b0 T"
b0 !
b0 /
b0 3
b0 -
b0 O"
b0 Q"
b0 R"
0&
b1001 >#
b1100100 =#
0%
#105000
1%
#110000
0%
1&
#115000
b11001000 ;
b11001000 :
b11001000 +
b11001000 T"
b110010000000000 !
b110010000000000 /
b1100100 3
0"
b1000 5
b1000 s
b1000 u
b1100100 -
b1100100 O"
b1100100 Q"
b1100100 R"
b1111011111001000 ,
b11110111 8
1r"
b11110111 *
b11110111 i"
b11110111 j"
0~"
0I
b1001 7
b1001 @
b1001 A
1U
0%"
b1001 1
b1001 z
b1001 {
11"
1q"
0}"
b1000 4
b1000 r
b1100100 N"
b11110110 f"
0H
1T
0$"
10"
1%
1'
b1001 $
b1001 )
b1001 =
b1001 w
b1100100 0
b1100100 #
b1100100 (
#120000
0%
#125000
1F"
1E"
1@"
1?"
1:"
19"
14"
13"
1."
1Q
01"
1L
1(#
1-"
1##
1("
0&#
1K
1"#
1F
1{"
1'"
1""
0.
1[
1W
1E
1t"
1z"
1.#
14#
1n"
1R
b1111 B
1n
1o"
1u"
1)#
1/#
15#
b11111111 k"
19#
1!"
b11111000 8
0I
0O
1U
1a
1g
1m
b11111000 7
b11111000 @
b11111000 A
0q
1r"
1x"
0~"
1,#
12#
18#
b111100110 *
b111100110 i"
b11100110 j"
0<#
b11111111 |
1J"
0%"
0+"
07"
0="
0C"
0I"
b100000000 1
b100000000 z
b0 {
0M"
b1111100010010000 ,
b10010000 ;
1G
1M
1S
1_
1e
1k
1o
1p"
1v"
1|"
1*#
10#
16#
1:#
b10010000 :
b11101111 9
b11101111 <
b11101111 e"
b0 6
1#"
1)"
15"
1;"
1A"
1G"
1K"
b1110111110010000 +
b1110111110010000 T"
b1100100000000000 !
b1100100000000000 /
b11001000 3
b11110111 2
b11110111 v
b1111011111001000 -
b1111011111001000 O"
b1111011111001000 Q"
b1111011111001000 R"
b111 5
b111 s
b111 u
b110 4
b110 r
b1111100010010000 N"
1%
0'
#130000
0%
#135000
0.
0j
1m
0i
0d
1g
0c
0W
0^
0R
1a
0K
0Q
b11111010 8
0]
0"#
0F
0L
b1 B
0X
b11110111 k"
0{"
0'"
0-"
b1 6
0!"
1I
0O
1U
b11111010 7
b11111010 @
b11111010 A
1[
0r"
0x"
1~"
b111101000 *
b111101000 i"
b11101000 j"
0&#
0""
0("
b11111000 |
0J"
b1111101000100000 N"
0%"
0+"
01"
b100000001 1
b100000001 z
b1 {
1M"
b1111101000100000 ,
b100000 ;
0G
0M
0S
1Y
0p"
0v"
0|"
1$#
b100000 :
b11110001 9
b11110001 <
b11110001 e"
0#"
0)"
1/"
0K"
b101 4
b101 r
b1111000100100000 +
b1111000100100000 T"
b1001000000000001 !
b1001000000000001 /
b10010000 3
b11111000 2
b11111000 v
b110 5
b110 s
b110 u
b1111100010010000 -
b1111100010010000 O"
b1111100010010000 Q"
b1111100010010000 R"
1%
#140000
0%
#145000
0t"
0o"
0I
1r"
b11111101 8
0E
0n"
b0 B
0n
b11110100 k"
09#
b11 6
1O
b11111101 7
b11111101 @
b11111101 A
1q
0x"
b111101011 *
b111101011 i"
b11101011 j"
1<#
b1111110101000000 N"
b100000011 1
b100000011 z
b11 {
1%"
b1111110101000000 ,
b1000000 ;
1M
0o
1v"
0:#
b1000000 :
b11110100 9
b11110100 <
b11110100 e"
1#"
b1111010001000000 +
b1111010001000000 T"
b10000000000011 !
b10000000000011 /
b100000 3
b11111010 2
b11111010 v
b100 4
b100 r
b1111101000100000 -
b1111101000100000 O"
b1111101000100000 Q"
b1111101000100000 R"
b101 5
b101 s
b101 u
1%
#150000
0%
#155000
1.
1j
0m
1i
1d
0g
1c
1^
0a
1]
1X
0[
1&#
b11 8
1W
1t"
1z"
1"#
b11111000 B
1R
1o"
1u"
b11111110 k"
1{"
b110 6
1!"
1I
0O
b100000011 7
b100000011 @
b11 A
0U
0r"
0x"
b111110001 *
b111110001 i"
b11110001 j"
0~"
b11111001 |
1J"
b1110000001 N"
1%"
1+"
b100000110 1
b100000110 z
b110 {
0M"
b1110000001 ,
b10000001 ;
1G
0M
1S
1p"
0v"
1|"
b10000000 :
b11111010 9
b11111010 <
b11111010 e"
0#"
1)"
1K"
b11 4
b11 r
b1111101010000000 +
b1111101010000000 T"
b100000000000110 !
b100000000000110 /
b1000000 3
b11111101 2
b11111101 v
b100 5
b100 s
b100 u
b1111110101000000 -
b1111110101000000 O"
b1111110101000000 Q"
b1111110101000000 R"
1%
#160000
0%
